{
  "global": {
    "color": {
      "red": {
        "400": {
          "value": "#d61414",
          "type": "color"
        },
        "500": {
          "value": "#e70909",
          "type": "color"
        }
      },
      "text": {
        "white": {
          "value": "white",
          "type": "color"
        }
      }
    },
    "spacing": {
      "small": {
        "value": "8",
        "type": "spacing"
      }
    },
    "radius": {
      "small": {
        "value": "8",
        "type": "borderRadius"
      }
    },
    "md": {
      "value": "600",
      "type": "fontWeights"
    }
  },
  "$themes": [],
  "$metadata": {
    "tokenSetOrder": [
      "global"
    ]
  }
}